vppcfg/__init__.py
vppcfg/_version.py
vppcfg/example.yaml
vppcfg/schema.yaml
vppcfg/tests.py
vppcfg/vppcfg.py
vppcfg/config/__init__.py
vppcfg/config/acl.py
vppcfg/config/address.py
vppcfg/config/bondethernet.py
vppcfg/config/bridgedomain.py
vppcfg/config/interface.py
vppcfg/config/lcp.py
vppcfg/config/loopback.py
vppcfg/config/mac.py
vppcfg/config/prefixlist.py
vppcfg/config/sflow.py
vppcfg/config/tap.py
vppcfg/config/test_acl.py
vppcfg/config/test_address.py
vppcfg/config/test_bondethernet.py
vppcfg/config/test_bridgedomain.py
vppcfg/config/test_interface.py
vppcfg/config/test_lcp.py
vppcfg/config/test_loopback.py
vppcfg/config/test_mac.py
vppcfg/config/test_prefixlist.py
vppcfg/config/test_tap.py
vppcfg/config/test_vxlan_tunnel.py
vppcfg/config/unittestyaml.py
vppcfg/config/vxlan_tunnel.py
vppcfg/vpp/__init__.py
vppcfg/vpp/applier.py
vppcfg/vpp/dumper.py
vppcfg/vpp/reconciler.py
vppcfg/vpp/vppapi.py
vppcfg-1.0.5.dist-info/licenses/LICENSE
vppcfg-1.0.5.dist-info/METADATA
vppcfg-1.0.5.dist-info/WHEEL
vppcfg-1.0.5.dist-info/entry_points.txt
vppcfg-1.0.5.dist-info/top_level.txt
vppcfg-1.0.5.dist-info/RECORD
