Metadata-Version: 2.4
Name: vppcfg
Version: 1.0.5
Summary: A configuration tool for Vector Packet Processing
Author-email: Pim van Pelt <pimg@ipng.ch>
License-Expression: Apache-2.0
Project-URL: Homepage, https://git.ipng.ch/ipng/vppcfg
Classifier: Programming Language :: Python :: 3
Classifier: Operating System :: OS Independent
Requires-Python: >=3.9
License-File: LICENSE
Requires-Dist: requests
Requires-Dist: importlib-metadata; python_version >= "3.8"
Requires-Dist: yamale
Requires-Dist: netaddr
Requires-Dist: vpp_papi
Dynamic: license-file
